setup.py
tap_utils/__init__.py
tap_utils/entity.py
tap_utils/postgres.py
tap_utils/sentiment.py
tap_utils/sqs.py
tap_utils/thread.py
tap_utils.egg-info/PKG-INFO
tap_utils.egg-info/SOURCES.txt
tap_utils.egg-info/dependency_links.txt
tap_utils.egg-info/not-zip-safe
tap_utils.egg-info/requires.txt
tap_utils.egg-info/top_level.txt