Metadata-Version: 1.0
Name: tap-utils
Version: 0.8
Summary: TAP utils
Home-page: UNKNOWN
Author: TAP
Author-email: tap8888@gmail.com
License: MIT
Platform: UNKNOWN
